[
  {
    "input": "ముందు సీటు రీడింగ్ లైట్ వెలిగించు.",
    "output": "ముందు సీటు రీడింగ్ లైట్ ఆన్ చేశాను."
  },
  {
    "input": "లోపలి లైట్లు కొంచెం డిమ్ చేయి.",
    "output": "అంతర్గత లైట్లను కొద్దిగా తగ్గించాను."
  },
  {
    "input": "హెడ్‌లైట్లు ఆన్ చేయి.",
    "output": "హెడ్‌లైట్లు ఆన్ అయ్యాయి."
  },
  {
    "input": "రాత్రి పూట హెడ్‌లైట్లు ఆపివేయి.",
    "output": "క్షమించండి, రాత్రి పూట ఇది సురక్షితం కాదు."
  },
  {
    "input": "డ్రైవర్ సీటును కొంచెం ముందుకు జరుపు.",
    "output": "డ్రైవర్ సీటును ముందుకు జరిపాను."
  },
  {
    "input": "నా సీటును వెనక్కి వంచండి.",
    "output": "మీ సీటును వెనక్కి వంచుతున్నాను."
  },
  {
    "input": "వెనుక కూర్చున్న వారి సీటును వెనక్కి జరుపు.",
    "output": "క్షమించండి, ఈ ఆపరేషన్‌కు అడ్మిన్ అనుమతి అవసరం."
  },
  {
    "input": "వెనుక సీటు టేబుల్ తెరవండి.",
    "output": "వెనుక సీటు టేబుల్ తెరుచుకుంది."
  },
  {
    "input": "టేబుల్ మూసివేయి.",
    "output": "టేబుల్ మూసివేస్తున్నాను."
  },
  {
    "input": "కారు లోపల లైట్ ఆపివేయి.",
    "output": "కారు లోపల లైట్ ఆఫ్ చేశాను."
  },
  {
    "input": "పొగమంచు లైట్లు ఆన్ చేయి.",
    "output": "పొగమంచు లైట్లు ఆన్ అయ్యాయి."
  },
  {
    "input": "ప్యాసింజర్ సీటును నంబర్ 2 మెమరీ సెట్టింగ్‌కు మార్చు.",
    "output": "క్షమించండి, ఈ ఫీచర్ యాక్సెస్ చేయడానికి అనుమతి లేదు."
  },
  {
    "input": "డ్రైవర్ సీటు ఎత్తును పెంచు.",
    "output": "డ్రైవర్ సీటు ఎత్తును పెంచుతున్నాను."
  },
  {
    "input": "కారు కదులుతున్నప్పుడు టేబుల్ ఎత్తును పెంచు.",
    "output": "క్షమించండి, కారు కదులుతున్నప్పుడు ఇది సురక్షితం కాదు."
  },
  {
    "input": "లోపలి లైట్లను కొంచెం ప్రకాశవంతం చేయి.",
    "output": "అంతర్గత లైట్లను ప్రకాశవంతం చేశాను."
  },
  {
    "input": "లైట్లను ఆటో మోడ్‌లో ఉంచు.",
    "output": "లైట్లను ఆటో మోడ్‌కు మార్చాను."
  },
  {
    "input": "నా సీటుకు నడుము సపోర్ట్ కొంచెం పెంచు.",
    "output": "మీ సీటుకు నడుము సపోర్ట్ పెంచుతున్నాను."
  },
  {
    "input": "వెనుక సీట్లను పూర్తిగా మడతపెట్టు.",
    "output": "ఈ చర్యకు అడ్మిన్ అనుమతి అవసరం, క్షమించండి."
  },
  {
    "input": "టేబుల్‌ను లాక్ చేయి.",
    "output": "టేబుల్ లాక్ చేయబడింది."
  },
  {
    "input": "సిటీలో ఉన్నప్పుడు హై బీమ్‌లు ఆన్ చేయి.",
    "output": "క్షమించండి, సిటీలో హై బీమ్‌లు సురక్షితం కాదు."
  },
  {
    "input": "లోపల లైట్లు ఆన్ చేయి.",
    "output": "అన్ని లోపలి లైట్లు ఆన్ అయ్యాయి."
  },
  {
    "input": "రీడింగ్ లైట్ డిమ్ చేయి.",
    "output": "రీడింగ్ లైట్ ప్రకాశం తగ్గించబడింది."
  },
  {
    "input": "కేవలం డోమ్ లైట్ మాత్రమే ఆన్ చేయి.",
    "output": "డోమ్ లైట్ ఆన్ చేశాను."
  },
  {
    "input": "వెనుక సీటు లైట్ పూర్తిగా ఆర్పేయి.",
    "output": "వెనుక సీటు లైట్ ఆఫ్ చేయబడింది."
  },
  {
    "input": "ఈ లైట్లకు రంగు మార్చగలవా?",
    "output": "క్షమించండి, ఈ లైట్లకు రంగు మార్చే అవకాశం లేదు."
  },
  {
    "input": "హెడ్‌లైట్లు ఆన్ చేయి.",
    "output": "హెడ్‌లైట్లు ఆన్ చేయబడ్డాయి."
  },
  {
    "input": "ఫాగ్ లైట్లు ఆఫ్ చేయి.",
    "output": "ఫాగ్ లైట్లు ఆఫ్ అయ్యాయి."
  },
  {
    "input": "రాత్రివేళ హెడ్‌లైట్లు పూర్తిగా ఆర్పేయి.",
    "output": "క్షమించండి, డ్రైవింగ్ చేసేటప్పుడు ఇది సురక్షితం కాదు."
  },
  {
    "input": "పార్కింగ్ లైట్లు ఆన్ చేయి.",
    "output": "పార్కింగ్ లైట్లు ఆన్ అయ్యాయి."
  },
  {
    "input": "నా సీటును కొంచెం ముందుకు జరుపు.",
    "output": "మీ సీటు ముందుకు జరపబడింది."
  },
  {
    "input": "వెనుక ప్రయాణీకుడి సీటు వెనక్కి జరుపు.",
    "output": "క్షమించండి, ఆ సీటును నియంత్రించడానికి అనుమతి లేదు."
  },
  {
    "input": "నా సీటును పూర్తిగా రిక్లైన్ చేయి.",
    "output": "మీ సీటు పూర్తిగా రిక్లైన్ చేయబడింది."
  },
  {
    "input": "డ్రైవర్ సీటు ఎత్తు పెంచు.",
    "output": "క్షమించండి, డ్రైవింగ్ చేసేటప్పుడు ఎత్తును పెంచడం సురక్షితం కాదు."
  },
  {
    "input": "వెనుక సీటుకు లంబార్ సపోర్ట్ ఆన్ చేయి.",
    "output": "వెనుక సీటుకు లంబార్ సపోర్ట్ ఆన్ చేయబడింది."
  },
  {
    "input": "నా సీటు హీటింగ్ ఆన్ చేయి.",
    "output": "మీ సీటు హీటింగ్ ఆన్ చేయబడింది."
  },
  {
    "input": "వెనుక సీటు టేబుల్ బయటికి తీయి.",
    "output": "వెనుక సీటు టేబుల్ బయటికి వచ్చింది."
  },
  {
    "input": "వెనుక టేబుల్‌ని లోపలికి పెట్టు.",
    "output": "వెనుక టేబుల్ లోపలికి తీసుకురాబడింది."
  },
  {
    "input": "టేబుల్ కొంచెం పైకి ఎత్తు.",
    "output": "టేబుల్ కొంచెం పైకి ఎత్తబడింది."
  },
  {
    "input": "ముందు టేబుల్‌ని పూర్తిగా లాక్ చేయి.",
    "output": "ముందు టేబుల్ లాక్ చేయబడింది."
  },
  {
    "input": "నేను డ్రైవింగ్ చేస్తున్నప్పుడు డ్రైవర్ టేబుల్ తెరవగలవా?",
    "output": "క్షమించండి, ఇది డ్రైవింగ్ చేస్తున్నప్పుడు సురక్షితం కాదు."
  },
  {
    "input": "లోపలి లైట్లు ఆన్ చేయి.",
    "output": "లోపలి లైట్లు ఆన్ చేశాను."
  },
  {
    "input": "రీడింగ్ లైట్ కొంచెం డిమ్ చేయి.",
    "output": "రీడింగ్ లైట్ ప్రకాశాన్ని తగ్గించాను."
  },
  {
    "input": "హెడ్‌లైట్స్ ఆన్ చేయి.",
    "output": "హెడ్‌లైట్స్ ఆన్ అయ్యాయి."
  },
  {
    "input": "ఫాగ్ లైట్లు ఆఫ్ చేయి.",
    "output": "ఫాగ్ లైట్లు ఆఫ్ చేశాను."
  },
  {
    "input": "నా సీటు కొంచెం ముందుకు జరుపు.",
    "output": "మీ సీటును ముందుకు జరిపాను."
  },
  {
    "input": "ప్రయాణీకుల సీటు వెనక్కి వంచండి.",
    "output": "ప్రయాణీకుల సీటును వంచాను."
  },
  {
    "input": "డ్రైవర్ సీటు ఎత్తు పెంచు.",
    "output": "డ్రైవర్ సీటు ఎత్తు పెంచాను."
  },
  {
    "input": "వెనుక టేబుల్ బయటకు తీయి.",
    "output": "వెనుక టేబుల్ సిద్ధంగా ఉంది."
  },
  {
    "input": "టేబుల్ లోపలికి పెట్టు.",
    "output": "టేబుల్ లోపలికి తీసుకున్నాను."
  },
  {
    "input": "టేబుల్ ఓపెన్ చేయి.",
    "output": "క్షమించండి, అధిక వేగంలో ఇది సురక్షితం కాదు."
  },
  {
    "input": "బయటి లైట్లు ఆటో మోడ్‌లో పెట్టు.",
    "output": "బయటి లైట్లను ఆటో మోడ్‌లో ఉంచాను."
  },
  {
    "input": "డ్రైవర్ సీటు మెమరీ సెట్టింగ్ మార్చు.",
    "output": "Admin అనుమతి లేకుండా మార్చలేను."
  },
  {
    "input": "రెండవ వరుసలో లైట్లు ఆన్ చేయి.",
    "output": "రెండవ వరుసలో లైట్లు ఆన్ అయ్యాయి."
  },
  {
    "input": "నా సీటుకు నడుము సపోర్ట్ పెంచు.",
    "output": "మీ నడుము సపోర్ట్ పెంచాను."
  },
  {
    "input": "టేబుల్ కొంచెం పైకి ఎత్తు.",
    "output": "టేబుల్ ఎత్తును పెంచాను."
  },
  {
    "input": "అన్ని లోపలి లైట్లు ఆపేయండి.",
    "output": "అన్ని లోపలి లైట్లు ఆఫ్ చేశాను."
  },
  {
    "input": "నా సీటు పూర్తిగా వెనక్కి జరుపు.",
    "output": "క్షమించండి, డ్రైవింగ్ చేసేటప్పుడు ఇది సురక్షితం కాదు."
  },
  {
    "input": "హెడ్‌లైట్ రంగు మార్చు.",
    "output": "క్షమించండి, ఆ ఫీచర్ అందుబాటులో లేదు."
  },
  {
    "input": "ఈ సీటు సెట్టింగ్‌లను సేవ్ చేయి.",
    "output": "ప్రస్తుత సీటు సెట్టింగ్‌లు సేవ్ అయ్యాయి."
  },
  {
    "input": "డోమ్ లైట్ ఆన్ చేయి.",
    "output": "డోమ్ లైట్ ఆన్ చేశాను."
  },
  {
    "input": "కారు లోపల లైట్లు ఆన్ చేయి.",
    "output": "అన్ని లోపలి లైట్లు ఆన్ చేశాను."
  },
  {
    "input": "ముందు సీటు రీడింగ్ లైట్ కొద్దిగా డిమ్ చేయి.",
    "output": "ముందు రీడింగ్ లైట్ ప్రకాశం తగ్గించాను."
  },
  {
    "input": "డోమ్ లైట్ బ్రైట్నెస్ పెంచు.",
    "output": "డోమ్ లైట్ ప్రకాశం పెంచాను."
  },
  {
    "input": "వెనుక సీటు లైట్లు ఆఫ్ చేయి.",
    "output": "వెనుక సీటు లైట్లు ఆఫ్ చేశాను."
  },
  {
    "input": "యాంబియంట్ లైటింగ్ రంగును నీలం రంగులోకి మార్చు.",
    "output": "రంగు మార్చడానికి, సెట్టింగ్స్ ఉపయోగించాల్సి ఉంటుంది."
  },
  {
    "input": "హెడ్‌లైట్లు ఆన్ చేయి.",
    "output": "హెడ్‌లైట్లు ఆన్ చేశాను."
  },
  {
    "input": "హెడ్‌లైట్‌లను ఆటో మోడ్‌లో పెట్టు.",
    "output": "హెడ్‌లైట్‌లు ఆటో మోడ్‌లో ఉన్నాయి."
  },
  {
    "input": "ఫాగ్ లైట్లు ఆన్ చేయి.",
    "output": "ఫాగ్ లైట్లు ఆన్ చేశాను."
  },
  {
    "input": "డ్రైవర్ సైడ్ లైట్ ఆఫ్ చేయి.",
    "output": "క్షమించండి, ఒకవైపు లైట్ ఆఫ్ చేయడం సాధ్యం కాదు."
  },
  {
    "input": "రాత్రిపూట హెడ్‌లైట్లు ఆఫ్ చేయి.",
    "output": "క్షమించండి, ఇది సురక్షితం కాదు. హెడ్‌లైట్లు ఆన్లో ఉంచుతాను."
  },
  {
    "input": "నా సీటును కొంచెం ముందుకు జరుపు.",
    "output": "సీటును కొద్దిగా ముందుకు జరిపాను."
  },
  {
    "input": "కో-డ్రైవర్ సీటు వెనక్కి వంచండి.",
    "output": "కో-డ్రైవర్ సీటు రిక్లైన్ చేశాను."
  },
  {
    "input": "వెనుక సీటును నిటారుగా చేయి.",
    "output": "వెనుక సీటును నిటారుగా మార్చాను."
  },
  {
    "input": "డ్రైవింగ్ చేస్తున్నప్పుడు నా సీటును పూర్తిగా వెనక్కి జరుపు.",
    "output": "క్షమించండి, డ్రైవింగ్లో పూర్తి సర్దుబాట్లు సురక్షితం కాదు."
  },
  {
    "input": "సీటు మెమరీ పొజిషన్ 2కి సెట్ చేయి.",
    "output": "సీటు మెమరీ 2కి సర్దుబాటు చేశాను."
  },
  {
    "input": "వెనుక ప్యాసింజర్ సీటు హీటింగ్ ఆన్ చేయి.",
    "output": "వెనుక సీటు హీటింగ్ ఆన్ చేశాను."
  },
  {
    "input": "వెనుక సీటు టేబుల్ పైకి ఎత్తు.",
    "output": "వెనుక సీటు టేబుల్ పైకి ఎత్తాను."
  },
  {
    "input": "నా టేబుల్ లోపలికి మడుచు.",
    "output": "మీ టేబుల్ లోపలికి మడిచాను."
  },
  {
    "input": "ముందు ప్యాసింజర్ టేబుల్ బయటికి పెట్టు.",
    "output": "ముందు ప్యాసింజర్ టేబుల్ ఏర్పాటు చేశాను."
  },
  {
    "input": "ఈ టేబుల్ పూర్తిగా తీసివేయి.",
    "output": "క్షమించండి, టేబుల్‌ను తొలగించే అనుమతి నాకు లేదు."
  },
  {
    "input": "లోపల లైట్లు వెలిగించు.",
    "output": "అంతర్గత లైట్లు వెలిగించబడ్డాయి."
  },
  {
    "input": "క్యాబిన్ లైట్ కొంచెం డిమ్ చేయి.",
    "output": "కాంతి స్థాయి తగ్గించబడింది."
  },
  {
    "input": "హెడ్‌లైట్స్ ఆన్ చేయి.",
    "output": "హెడ్‌లైట్స్ వెలిగించబడ్డాయి."
  },
  {
    "input": "పొగమంచు లైట్లు వేయు.",
    "output": "క్షమించండి, డ్రైవర్ అనుమతి లేకుండా సాధ్యం కాదు."
  },
  {
    "input": "డ్రైవర్ సీటును ముందుకు జరుపు.",
    "output": "డ్రైవర్ సీటు ముందుకు కదులుతోంది."
  },
  {
    "input": "పక్కన సీటును కొంచెం వెనక్కి జరుపు.",
    "output": "సహ-ప్రయాణీకుల సీటు వెనక్కి జరుపబడింది."
  },
  {
    "input": "నా సీటుకు నడుము సపోర్ట్ పెంచు.",
    "output": "నడుము సపోర్ట్ సర్దుబాటు చేయబడింది."
  },
  {
    "input": "ముందున్న టేబుల్ తెరచు.",
    "output": "టేబుల్ విప్పబడుతోంది."
  },
  {
    "input": "ఈ టేబుల్ కొంచెం పైకి ఎత్తు.",
    "output": "క్షమించండి, కదులుతున్నప్పుడు ఇది సురక్షితం కాదు."
  },
  {
    "input": "నా రీడింగ్ లైట్ ఆన్ చేయి.",
    "output": "మీ రీడింగ్ లైట్ వెలిగించబడింది."
  },
  {
    "input": "పక్క సీటు ఎత్తును కొద్దిగా తగ్గించు.",
    "output": "సహ-ప్రయాణీకుల సీటు ఎత్తు తగ్గించబడింది."
  },
  {
    "input": "హెడ్‌లైట్స్ హై బీమ్ లో పెట్టు.",
    "output": "నేను డ్రైవర్ అనుమతి లేకుండా హై బీమ్ మార్చలేను."
  },
  {
    "input": "ఈ సీటు సెట్టింగులను సేవ్ చేయి.",
    "output": "మీ సెట్టింగులు ప్రొఫైల్ 1 లో సేవ్ చేయబడ్డాయి."
  },
  {
    "input": "టేబుల్ లోపలికి పెట్టు.",
    "output": "టేబుల్ లోపలికి మడవబడుతోంది."
  },
  {
    "input": "వెనుక ఎడమ వైపు ప్యాసింజర్ లైట్ ఆన్ చేయి.",
    "output": "వెనుక ఎడమ ప్యాసింజర్ లైట్ వెలిగించబడింది."
  },
  {
    "input": "డ్రైవర్ సీటును పూర్తిగా వెనక్కి జరుపు.",
    "output": "క్షమించండి, డ్రైవింగ్ చేస్తున్నప్పుడు ఇది సురక్షితం కాదు."
  },
  {
    "input": "పార్కింగ్ లైట్లు వెలిగించు.",
    "output": "పార్కింగ్ లైట్లు వెలిగించబడ్డాయి."
  },
  {
    "input": "నా సీటు ప్రొఫైల్ 2 లోడ్ చేయి.",
    "output": "ప్రొఫైల్ 2 సెట్టింగులు లోడ్ చేయబడ్డాయి."
  },
  {
    "input": "లోపలి లైట్లను కొంచెం ప్రకాశవంతం చేయి.",
    "output": "అంతర్గత కాంతి పెంచబడింది."
  },
  {
    "input": "టేబుల్ ప్రస్తుత స్థితి ఏమిటి?",
    "output": "టేబుల్ ప్రస్తుతం ముడుచుకొని ఉంది."
  },
  {
    "input": "లోపలి లైట్లు కొద్దిగా డిమ్ చేయి.",
    "output": "సరే, లోపలి లైట్లు డిమ్ చేశాను."
  },
  {
    "input": "వెనుక సీటు లైట్ ఆన్ చేయి.",
    "output": "వెనుక సీటు లైట్ ఆన్ చేశాను."
  },
  {
    "input": "హెడ్‌లైట్లు ఆన్ చేయి.",
    "output": "హెడ్‌లైట్లు ఆన్ చేశాను."
  },
  {
    "input": "ఫాగ్ లైట్లు ఆన్ చేయి.",
    "output": "ఫాగ్ లైట్లు ఆన్ చేశాను."
  },
  {
    "input": "నా సీటు కొద్దిగా వెనక్కి జరుపు.",
    "output": "సరే, మీ సీటు వెనక్కి జరిపాను."
  },
  {
    "input": "ముందు సీటును ముందుకు జరుపు.",
    "output": "ముందు సీటును ముందుకు జరిపాను."
  },
  {
    "input": "వెనుక సీటును రిక్లైన్ చేయి.",
    "output": "వెనుక సీటును రిక్లైన్ చేశాను."
  },
  {
    "input": "వెనుక టేబుల్స్ పైకి ఎత్తు.",
    "output": "సరే, వెనుక టేబుల్స్ పైకి ఎత్తాను."
  },
  {
    "input": "నా టేబుల్ సెట్ చేయి.",
    "output": "మీ టేబుల్ సెట్ చేశాను."
  },
  {
    "input": "కేబిన్ లైట్లు పూర్తిగా ఆఫ్ చేయి.",
    "output": "కేబిన్ లైట్లు పూర్తిగా ఆఫ్ చేశాను."
  },
  {
    "input": "డ్రైవర్ సీటు ఎత్తు పెంచు.",
    "output": "సరే, డ్రైవర్ సీటు ఎత్తు పెంచాను."
  },
  {
    "input": "హెడ్‌లైట్ లెవెల్ కొద్దిగా తగ్గించు.",
    "output": "హెడ్‌లైట్ లెవెల్ తగ్గించాను."
  },
  {
    "input": "ముందు ప్యాసింజర్ టేబుల్ కిందకు దించు.",
    "output": "ముందు ప్యాసింజర్ టేబుల్ కిందకు దించాను."
  },
  {
    "input": "నడుపుతున్నప్పుడు డ్రైవర్ సీటు వెనక్కి జరుపు.",
    "output": "క్షమించండి, నడుపుతున్నప్పుడు డ్రైవర్ సీటు సర్దుబాటు చేయడం సురక్షితం కాదు."
  },
  {
    "input": "బ్రేక్ లైట్లు ఆన్ చేయి.",
    "output": "బ్రేక్ లైట్లు మాన్యువల్‌గా ఆన్ చేయలేను. అవి బ్రేక్ వేసినప్పుడు మాత్రమే వెలుగుతాయి."
  },
  {
    "input": "డ్రైవర్ సీటు వెనుక లైట్ ఎరుపు రంగులోకి మార్చు.",
    "output": "క్షమించండి, రంగు మార్చే ఫీచర్ అందుబాటులో లేదు."
  },
  {
    "input": "నా సీటును 'సౌకర్యవంతమైన' మోడ్‌కి సెట్ చేయి.",
    "output": "మీ సీటును 'సౌకర్యవంతమైన' మోడ్‌కి సెట్ చేశాను."
  },
  {
    "input": "డ్రైవర్ ముందు టేబుల్ బయటకు తీయి.",
    "output": "క్షమించండి, డ్రైవర్ ముందు టేబుల్ ఏర్పాటు చేయడం సురక్షితం కాదు."
  },
  {
    "input": "వెనుక పార్కింగ్ లైట్లను బ్లింక్ చేయి.",
    "output": "క్షమించండి, పార్కింగ్ లైట్లను బ్లింక్ చేసే ఫంక్షన్ అందుబాటులో లేదు."
  },
  {
    "input": "లైట్లు ఆన్ చేయి.",
    "output": "ఏ లైట్లు ఆన్ చేయాలి? లోపలివా లేక బయటివా?"
  },
  {
    "input": "లోపలి లైట్లు కొంచెం డిమ్ చేయి.",
    "output": "లోపలి లైట్ల ప్రకాశం తగ్గించబడింది."
  },
  {
    "input": "డ్రైవర్ సీటును కొంచెం ముందుకు జరుపు.",
    "output": "డ్రైవర్ సీటు ముందుకు కదిలించబడింది."
  },
  {
    "input": "పాసింజర్ సైడ్ రీడింగ్ లైట్ ఆన్ చేయి.",
    "output": "పాసింజర్ రీడింగ్ లైట్ వెలిగించబడింది."
  },
  {
    "input": "హెడ్‌లైట్లు ఆన్ చేయగలవా?",
    "output": "హెడ్‌లైట్లు ఆన్ చేయబడ్డాయి."
  },
  {
    "input": "వెనుక సీటు టేబుల్‌ని పైకి ఎత్తు.",
    "output": "వెనుక సీటు టేబుల్ పైకి లేపబడింది."
  },
  {
    "input": "ముందు సీటును వెనక్కి రిక్లైన్ చేయి.",
    "output": "ముందు సీటు వెనక్కి వంచబడింది."
  },
  {
    "input": "బయటి లైట్లు హై బీమ్‌కి మార్చు.",
    "output": "హై బీమ్‌లు ఆన్ చేయబడ్డాయి."
  },
  {
    "input": "మూడో వరుస సీటుకు లంబార్ సపోర్ట్ పెంచు.",
    "output": "మూడో వరుస సీటు లంబార్ సపోర్ట్ పెంచబడింది."
  },
  {
    "input": "క్యాబిన్ లైట్లు పూర్తిగా ఆపేయగలవా?",
    "output": "క్యాబిన్ లైట్లు ఆపివేయబడ్డాయి."
  },
  {
    "input": "నాకు సౌకర్యంగా ఉండేలా నా సీటును సర్దుబాటు చేయి.",
    "output": "మీ ప్రాధాన్యతలకు అనుగుణంగా సీటు సర్దుబాటు చేయబడింది."
  },
  {
    "input": "డిమ్ లైట్లను ఆన్ చేయి.",
    "output": "డిమ్ లైట్లు ఆన్ చేయబడ్డాయి."
  },
  {
    "input": "కుడి వైపు వెనుక సీటును కనీస స్థాయికి జరుపు.",
    "output": "కుడి వైపు వెనుక సీటు కనీస స్థాయికి సర్దుబాటు చేయబడింది."
  },
  {
    "input": "డ్రైవర్ సీటును ఎత్తుగా చేయి.",
    "output": "డ్రైవర్ సీటు ఎత్తు పెంచబడింది."
  },
  {
    "input": "కుడి వైపు టేబుల్‌ని దిగువకు దించు.",
    "output": "కుడి వైపు టేబుల్ దిగువకు దించబడింది."
  },
  {
    "input": "లైట్లు పూర్తిగా ఆపేయ్.",
    "output": "దయచేసి ఏ లైట్లు ఆపాలో స్పష్టం చేయండి."
  },
  {
    "input": "కారు నడుపుతుండగా డ్రైవర్ సీటును పూర్తిగా వెనక్కి వంచేయ్.",
    "output": "క్షమించండి, డ్రైవింగ్ చేస్తున్నప్పుడు ఇది సురక్షితం కాదు."
  },
  {
    "input": "నేను వెనుక సీట్లో ఉన్నాను, డ్రైవర్ సీటు సెట్టింగ్‌లు మార్చు.",
    "output": "క్షమించండి, డ్రైవర్ సీటును మార్చడానికి మీకు అనుమతి లేదు."
  },
  {
    "input": "హై బీమ్‌లను నిరంతరం ఆన్ చేయి.",
    "output": "ఇది ఎదుటివారికి ఇబ్బంది కలిగిస్తుంది, అందుకే చేయలేను."
  },
  {
    "input": "నా వైపు టేబుల్‌ను అడ్డంగా తిప్పు.",
    "output": "క్షమించండి, ప్రస్తుతం ఆ అమరిక సాధ్యం కాదు."
  },
  {
    "input": "పాసింజర్ సీటును పూర్తిగా ముందుకు జరుపు.",
    "output": "దయచేసి ఎంత దూరం కావాలో చెప్పగలరా? పూర్తిగా జరపడం సురక్షితం కాదు."
  },
  {
    "input": "నా సీటును కొంచెం ముందుకు జరుపు.",
    "output": "మీ సీటు ముందుకు జరపబడింది."
  },
  {
    "input": "లోపల లైట్లు ఆన్ చేయి.",
    "output": "లోపలి లైట్లు ఆన్ అయ్యాయి."
  },
  {
    "input": "ముందు ప్రయాణీకుల సీటును పూర్తిగా రిక్లైన్ చేయి.",
    "output": "ప్రయాణీకుల సీటు రిక్లైన్ చేయబడింది."
  },
  {
    "input": "రీడింగ్ లైట్ ప్రకాశం తగ్గించు.",
    "output": "రీడింగ్ లైట్ ప్రకాశం తగ్గించబడింది."
  },
  {
    "input": "నేను డ్రైవింగ్ చేస్తున్నాను, నా సీటు పూర్తిగా రిక్లైన్ చేయి.",
    "output": "క్షమించండి, డ్రైవింగ్ చేస్తున్నప్పుడు పూర్తిగా రిక్లైన్ చేయడం సురక్షితం కాదు."
  },
  {
    "input": "హెడ్‌లైట్లు ఆన్ చేయి.",
    "output": "హెడ్‌లైట్లు ఆన్ చేయబడ్డాయి."
  },
  {
    "input": "వెనుక సీటు టేబుల్ బయటకు తీయి.",
    "output": "వెనుక సీటు టేబుల్ బయటకు వచ్చింది."
  },
  {
    "input": "క్యాబిన్ లైట్ ను ప్రకాశవంతం చేయి.",
    "output": "క్యాబిన్ లైట్ ప్రకాశవంతం చేయబడింది."
  },
  {
    "input": "టేబుల్ మడతపెట్టు.",
    "output": "టేబుల్ మడతపెట్టబడింది."
  },
  {
    "input": "ఫాగ్ లైట్లు ఆన్ చేయి.",
    "output": "ఫాగ్ లైట్లు ఆన్ అయ్యాయి."
  },
  {
    "input": "డ్రైవర్ సీటును వెనక్కి జరుపు.",
    "output": "క్షమించండి, మీకు డ్రైవర్ సీటును సర్దుబాటు చేయడానికి అనుమతి లేదు."
  },
  {
    "input": "నడుము సపోర్ట్ కొంచెం పెంచు.",
    "output": "నడుము సపోర్ట్ సర్దుబాటు చేయబడింది."
  },
  {
    "input": "అన్ని లోపలి లైట్లు ఆపివేయి.",
    "output": "అన్ని లోపలి లైట్లు ఆపివేయబడ్డాయి."
  },
  {
    "input": "రాత్రిపూట హెడ్‌లైట్లు ఆపివేయి.",
    "output": "క్షమించండి, రాత్రిపూట హెడ్‌లైట్లు ఆపివేయడం చట్టబద్ధం కాదు మరియు సురక్షితం కాదు."
  },
  {
    "input": "పార్కింగ్ లైట్లు ఆన్ చేయి.",
    "output": "పార్కింగ్ లైట్లు ఆన్ అయ్యాయి."
  },
  {
    "input": "వెనుక సీటు లైట్ ఆపివేయి.",
    "output": "వెనుక సీటు లైట్ ఆపివేయబడింది."
  },
  {
    "input": "హై బీమ్ ఆన్ చేయి.",
    "output": "క్షమించండి, ఎదురుగా వాహనాలు వస్తున్నాయి. ఇది సురక్షితం కాదు."
  },
  {
    "input": "నా సీటు పొజిషన్ ని 'ప్రయాణం' గా సేవ్ చేయి.",
    "output": "సీటు పొజిషన్ సేవ్ చేయబడింది."
  },
  {
    "input": "డ్రైవింగ్ చేస్తుండగా టేబుల్ ఎత్తును పెంచు.",
    "output": "క్షమించండి, డ్రైవింగ్ చేస్తున్నప్పుడు టేబుల్ సర్దుబాటు చేయడం సురక్షితం కాదు."
  },
  {
    "input": "వెనుక సీటు ఎత్తు పెంచు.",
    "output": "వెనుక సీటు ఎత్తు పెంచబడింది."
  },
  {
    "input": "క్యాబిన్ లైట్లు ఆన్ చేయి.",
    "output": "క్యాబిన్ లైట్లు ఆన్ చేశాను."
  },
  {
    "input": "హెడ్‌లైట్లు వెలిగించు.",
    "output": "హెడ్‌లైట్లు వెలిగించాను."
  },
  {
    "input": "డ్రైవర్ సీటును కొంచెం ముందుకు జరుపు.",
    "output": "సీటును ముందుకు జరిపాను."
  },
  {
    "input": "వెనుక సీటు టేబుల్‌ను బయటకు తీయి.",
    "output": "టేబుల్ సిద్ధంగా ఉంది."
  },
  {
    "input": "లోపలి లైట్లను డిమ్ చేయి.",
    "output": "లైట్లను డిమ్ చేశాను."
  },
  {
    "input": "ముందు ప్యాసింజర్ సీటును వెనక్కి వంచండి.",
    "output": "సీటును వెనక్కి వంచాను."
  },
  {
    "input": "ఫాగ్ లైట్లు ఆన్ చేయి.",
    "output": "ఫాగ్ లైట్లు ఆన్ అయ్యాయి."
  },
  {
    "input": "ప్యాసింజర్ టేబుల్‌ను మడతపెట్టు.",
    "output": "టేబుల్ మడతపెట్టబడింది."
  },
  {
    "input": "నా రీడింగ్ లైట్ ప్రకాశాన్ని పెంచు.",
    "output": "రీడింగ్ లైట్ ప్రకాశం పెంచబడింది."
  },
  {
    "input": "డ్రైవర్ సీటు లంబార్ సపోర్ట్‌ను సర్దుబాటు చేయి.",
    "output": "లంబార్ సపోర్ట్ సర్దుబాటు చేశాను."
  },
  {
    "input": "ఒక్కసారి హై బీమ్‌లు వేసి ఆర్పేయ్.",
    "output": "హై బీమ్‌లు ఫ్లాష్ అయ్యాయి."
  },
  {
    "input": "వెనుక టేబుల్ కొంచెం పైకి ఎత్తు.",
    "output": "టేబుల్ పైకి ఎత్తబడింది."
  },
  {
    "input": "లోపల ఉన్న అన్ని లైట్లను ఆపేయ్.",
    "output": "అన్ని లోపలి లైట్లు ఆపివేశాను."
  },
  {
    "input": "నా సీటును కొద్దిగా పైకి లేపు.",
    "output": "సీటు ఎత్తును సర్దుబాటు చేశాను."
  },
  {
    "input": "డ్రైవర్ సీటును వెనక్కి జరుపు, కానీ వేగంగా.",
    "output": "క్షమించండి, అధిక వేగంతో సీటును జరపడం సురక్షితం కాదు."
  },
  {
    "input": "డ్రైవింగ్ చేస్తున్నప్పుడు హెడ్‌లైట్ల కోణాన్ని సర్దుబాటు చేయి.",
    "output": "క్షమించండి, ఈ సమయంలో హెడ్‌లైట్ల కోణాన్ని మార్చలేను."
  },
  {
    "input": "డ్రైవర్ టేబుల్ పెట్టండి, నేను చాలా కోణంలో తిరుగుతున్నాను.",
    "output": "ఇది సురక్షితం కాదు. టేబుల్ ఇప్పుడు తెరవలేను."
  },
  {
    "input": "హజార్డ్ లైట్లు ఆన్ చేయి.",
    "output": "హజార్డ్ లైట్లు ఆన్ అయ్యాయి."
  },
  {
    "input": "యాంబియంట్ లైట్ రంగును నీలం రంగులోకి మార్చు.",
    "output": "యాంబియంట్ లైట్ నీలం రంగులోకి మార్చబడింది."
  },
  {
    "input": "అన్ని సీట్లను వాటి అత్యధిక వెనుక స్థానానికి తీసుకెళ్లు.",
    "output": "క్షమించండి, అడ్మిన్ అనుమతి లేకుండా అన్ని సీట్లను ఒకేసారి మార్చలేను."
  },
  {
    "input": "క్యాబిన్ లైట్లను ఆన్ చేయి.",
    "output": "క్యాబిన్ లైట్లు ఆన్ అయ్యాయి."
  },
  {
    "input": "ముందున్న ప్యాసింజర్ సీటును కొంచెం ముందుకు జరుపు.",
    "output": "ముందు ప్యాసింజర్ సీటు ముందుకు జరిపాను."
  },
  {
    "input": "లోపలి లైట్లను డిమ్ చేయి.",
    "output": "లోపలి లైట్లు డిమ్ అయ్యాయి."
  },
  {
    "input": "నా సీటు రిక్లైన్ చేయి.",
    "output": "మీ సీటు రిక్లైన్ అవుతోంది."
  },
  {
    "input": "వెనుక టేబుల్‌ని పైకి ఎత్తు.",
    "output": "వెనుక టేబుల్ పైకి ఎత్తబడింది."
  },
  {
    "input": "హెడ్‌లైట్లను వెలిగించు.",
    "output": "హెడ్‌లైట్లు ఆన్ అయ్యాయి."
  },
  {
    "input": "నేను డ్రైవింగ్ చేస్తున్నప్పుడు నా సీటు పూర్తిగా వెనక్కి వంచేయి.",
    "output": "క్షమించండి, డ్రైవింగ్ చేస్తున్నప్పుడు ఇది సురక్షితం కాదు."
  },
  {
    "input": "వెనుక ప్యాసింజర్ సీటులో లంబర్ సపోర్ట్ పెంచు.",
    "output": "వెనుక సీటు లంబర్ సపోర్ట్ పెంచబడింది."
  },
  {
    "input": "అన్ని లోపలి లైట్లను ఆఫ్ చేయి.",
    "output": "అన్ని లోపలి లైట్లు ఆఫ్ అయ్యాయి."
  },
  {
    "input": "డ్రైవింగ్ చేస్తున్నప్పుడు ముందున్న టేబుల్ పూర్తిగా తెరువు.",
    "output": "క్షమించండి, డ్రైవింగ్ చేస్తున్నప్పుడు ఇది సురక్షితం కాదు."
  },
  {
    "input": "వెనుక ఎడమ వైపు సీటును వెనక్కి జరుపు.",
    "output": "వెనుక ఎడమ సీటు వెనక్కి జరిపాను."
  },
  {
    "input": "ముందు సీటు ప్యాసింజర్ రీడింగ్ లైట్ ఆన్ చేయి.",
    "output": "ముందు సీటు రీడింగ్ లైట్ ఆన్ అయ్యింది."
  },
  {
    "input": "ఫాగ్ లైట్లను ఆన్ చేయి.",
    "output": "ఫాగ్ లైట్లు ఆన్ అయ్యాయి."
  },
  {
    "input": "నా సీటును మెమరీ పొజిషన్ 1కి మార్చు.",
    "output": "మీ సీటు మెమరీ పొజిషన్ 1కి మార్చబడింది."
  },
  {
    "input": "ముందు వెళ్ళే కారుకి హై బీమ్ కొట్టు.",
    "output": "క్షమించండి, ఇది సురక్షితం కాదు మరియు చట్టవిరుద్ధం."
  },
  {
    "input": "వెనుక టేబుల్‌ని మడతపెట్టు.",
    "output": "వెనుక టేబుల్ మడతపెట్టబడింది."
  },
  {
    "input": "డ్రైవర్ పక్క సీటును కిందికి దించు.",
    "output": "డ్రైవర్ పక్క సీటును కిందికి దించాను."
  },
  {
    "input": "ప్రయాణీకుల సీటును పూర్తిగా రిక్లైన్ చేయి.",
    "output": "క్షమించండి, ప్రయాణీకుల అనుమతి లేకుండా చేయలేను."
  },
  {
    "input": "డోమ్ లైట్‌ను ప్రకాశవంతం చేయి.",
    "output": "డోమ్ లైట్ ప్రకాశం పెరిగింది."
  },
  {
    "input": "అన్ని బాహ్య లైట్లను ఆఫ్ చేయి.",
    "output": "అన్ని బాహ్య లైట్లు ఆఫ్ అయ్యాయి."
  },
  {
    "input": "క్యాబిన్ లైట్లు ఆన్ చేయి.",
    "output": "క్యాబిన్ లైట్లు ఆన్ చేయబడ్డాయి."
  },
  {
    "input": "రీడింగ్ లైట్ ప్రకాశం తగ్గించు.",
    "output": "రీడింగ్ లైట్ ప్రకాశం తగ్గించబడింది."
  },
  {
    "input": "అన్ని లోపలి లైట్లు ఆఫ్ చెయ్.",
    "output": "లోపలి లైట్లన్నీ ఆఫ్ చేయబడ్డాయి."
  },
  {
    "input": "వెనుక సీటు లైట్లు డిమ్ చేయి.",
    "output": "వెనుక సీటు లైట్లు డిమ్ చేయబడ్డాయి."
  },
  {
    "input": "హెడ్‌లైట్లు వెలిగించు.",
    "output": "హెడ్‌లైట్లు ఆన్ చేయబడ్డాయి."
  },
  {
    "input": "ఫాగ్ లైట్లు ఆన్ చెయ్.",
    "output": "ఫాగ్ లైట్లు ఆన్ చేయబడ్డాయి."
  },
  {
    "input": "డ్రైవింగ్ చేస్తున్నప్పుడు హెడ్‌లైట్లు ఆఫ్ చేయి.",
    "output": "క్షమించండి, డ్రైవింగ్ చేస్తున్నప్పుడు ఇది సురక్షితం కాదు."
  },
  {
    "input": "పార్కింగ్ లైట్లు ఆఫ్ చేయి.",
    "output": "పార్కింగ్ లైట్లు ఆఫ్ చేయబడ్డాయి."
  },
  {
    "input": "నా సీటును కొద్దిగా ముందుకు జరుపు.",
    "output": "మీ సీటు కొద్దిగా ముందుకు జరపబడింది."
  },
  {
    "input": "ప్యాసింజర్ సీటును వెనక్కి రిక్లైన్ చేయి.",
    "output": "ప్యాసింజర్ సీటు రిక్లైన్ చేయబడింది."
  },
  {
    "input": "డ్రైవింగ్ చేస్తున్నప్పుడు డ్రైవర్ సీటును పూర్తిగా వెనక్కి జరుపు.",
    "output": "క్షమించండి, డ్రైవింగ్ చేస్తున్నప్పుడు ఇది సురక్షితం కాదు."
  },
  {
    "input": "సీటు మెమొరీ పొజిషన్ 2కి సెట్ చేయి.",
    "output": "సీటు మెమొరీ పొజిషన్ 2కి సెట్ చేయబడింది."
  },
  {
    "input": "ఎడమ వైపు వెనుక సీటు కూలర్ ఆన్ చేయి.",
    "output": "ఎడమ వైపు వెనుక సీటు కూలర్ ఆన్ చేయబడింది."
  },
  {
    "input": "వెనుక సీట్లన్నింటినీ నిటారుగా చేయి.",
    "output": "వెనుక సీట్లన్నీ నిటారుగా చేయబడ్డాయి."
  },
  {
    "input": "నా సీటు లంబార్ సపోర్ట్ పెంచు.",
    "output": "లంబార్ సపోర్ట్ పెంచబడింది."
  },
  {
    "input": "వెనుక కూర్చున్న వ్యక్తి సీటును తరలించు.",
    "output": "క్షమించండి, ఇది అడ్మిన్ అనుమతి లేకుండా చేయలేను."
  },
  {
    "input": "నా సీటును ఎత్తుగా చేయి.",
    "output": "మీ సీటు ఎత్తుగా చేయబడింది."
  },
  {
    "input": "ముందు ప్యాసింజర్ టేబుల్ తెరచు.",
    "output": "ముందు ప్యాసింజర్ టేబుల్ తెరవబడింది."
  },
  {
    "input": "వెనుక సీటు టేబుల్ కిందకు దించు.",
    "output": "వెనుక సీటు టేబుల్ కిందకు దించబడింది."
  },
  {
    "input": "టేబుల్ ని మూసేయ్.",
    "output": "టేబుల్ మూసివేయబడింది."
  },
  {
    "input": "లోపల లైట్ కొద్దిగా డిమ్ చేయగలవా?",
    "output": "అవును, లైట్ డిమ్ చేశాను."
  },
  {
    "input": "డ్రైవర్ సీటును కొంచెం ముందుకు జరుపు.",
    "output": "డ్రైవర్ సీటు ముందుకు జరిపాను."
  },
  {
    "input": "హెడ్‌లైట్స్ ఆన్ చెయ్.",
    "output": "హెడ్‌లైట్స్ ఆన్ చేశాను."
  },
  {
    "input": "వెనక కుడి సీటు టేబుల్‌ను బయటకు తీయగలవా?",
    "output": "టేబుల్ బయటకు తీశాను."
  },
  {
    "input": "నా వైపు రీడింగ్ లైట్ ఆన్ చెయ్.",
    "output": "రీడింగ్ లైట్ ఆన్ చేశాను."
  },
  {
    "input": "ముందు ప్యాసింజర్ సీటును వెనక్కి వంచండి.",
    "output": "క్షమించండి, ఈ సమయంలో ప్యాసింజర్ సీటును వంచలేను."
  },
  {
    "input": "ఫాగ్ లైట్స్ ఆన్ చెయ్.",
    "output": "ఫాగ్ లైట్స్ ఆన్ చేశాను."
  },
  {
    "input": "లోపల ఉన్న అన్ని లైట్లు ఆపివేయ్.",
    "output": "అన్ని అంతర్గత లైట్లు ఆపివేశాను."
  },
  {
    "input": "డ్రైవర్ సీటును ఇంకా వెనక్కి జరుపు.",
    "output": "క్షమించండి, డ్రైవింగ్ చేస్తున్నప్పుడు ఇది సురక్షితం కాదు."
  },
  {
    "input": "టేబుల్‌ను లోపలికి పెట్టు.",
    "output": "టేబుల్‌ను లోపలికి పెట్టాను."
  },
  {
    "input": "నా సీటుకు నడుము సపోర్ట్ పెంచు.",
    "output": "నడుము సపోర్ట్ పెంచాను."
  },
  {
    "input": "హై బీమ్స్ ఆన్ చెయ్.",
    "output": "క్షమించండి, ఈ అభ్యర్థనను సురక్షితంగా నిర్వహించలేను."
  },
  {
    "input": "లోపల లైట్లు కొంచెం ప్రకాశవంతంగా చేయి.",
    "output": "లైట్లు ప్రకాశవంతంగా చేశాను."
  },
  {
    "input": "ఈ సీటు సెట్టింగ్‌ను 'నా స్థానం' అని సేవ్ చేయి.",
    "output": "'నా స్థానం' గా సేవ్ చేయబడింది."
  },
  {
    "input": "టేబుల్ కొంచెం పైకి ఎత్తు.",
    "output": "టేబుల్ పైకి ఎత్తాను."
  },
  {
    "input": "లైట్లను ఆటో మోడ్‌లో పెట్టు.",
    "output": "లైట్లు ఇప్పుడు ఆటో మోడ్‌లో ఉన్నాయి."
  },
  {
    "input": "వెనక మధ్య సీటును కొంచెం ముందుకు జరుపు.",
    "output": "క్షమించండి, ఈ సీటును ఇప్పుడు జరపడానికి అనుమతి లేదు."
  },
  {
    "input": "డోమ్ లైట్ ఆన్ చెయ్.",
    "output": "డోమ్ లైట్ ఆన్ చేశాను."
  },
  {
    "input": "'గెస్ట్' సీటు సెట్టింగ్ లోడ్ చెయ్.",
    "output": "'గెస్ట్' సెట్టింగ్‌ను లోడ్ చేశాను."
  },
  {
    "input": "వెనక ఎడమ సీటు టేబుల్‌ను బయటకు తీయ్.",
    "output": "క్షమించండి, సీట్‌బెల్ట్ భద్రతా కారణాల వల్ల కుదరదు."
  },
  {
    "input": "లోపలి లైట్లు కొంచెం డిమ్ చేయగలవా?",
    "output": "లోపలి లైట్లు డిమ్ చేశాను."
  },
  {
    "input": "కార్ లోపల లైట్లు కొంచెం పెంచండి.",
    "output": "లైట్లు ప్రకాశవంతం చేశాను."
  },
  {
    "input": "వెనుక రీడింగ్ లైట్ ఆన్ చేయి.",
    "output": "వెనుక రీడింగ్ లైట్ ఆన్ చేశాను."
  },
  {
    "input": "హెడ్‌లైట్లు ఆన్ చేయి.",
    "output": "హెడ్‌లైట్లు ఆన్ చేశాను."
  },
  {
    "input": "ఈ రాత్రిపూట హెడ్‌లైట్లు ఆఫ్ చేయి.",
    "output": "క్షమించండి, రాత్రిపూట ఇది సురక్షితం కాదు."
  },
  {
    "input": "ఫాగ్ లైట్లు ఆన్ చేయగలవా?",
    "output": "ఫాగ్ లైట్లు ఆన్ చేశాను."
  },
  {
    "input": "నా సీటును కొంచెం ముందుకు జరుపు.",
    "output": "మీ సీటును ముందుకు జరిపాను."
  },
  {
    "input": "వెనుక సీటును కొద్దిగా వెనక్కి వంచగలవా?",
    "output": "వెనుక సీటు వంచాను."
  },
  {
    "input": "డ్రైవర్ సీటును పూర్తిగా వెనక్కి వంచగలవా?",
    "output": "క్షమించండి, డ్రైవింగ్ చేసేటప్పుడు ఇది సురక్షితం కాదు."
  },
  {
    "input": "నా సీటు ఎత్తును కొంచెం పెంచు.",
    "output": "మీ సీటు ఎత్తు పెంచాను."
  },
  {
    "input": "నా సీటుకు నడుము సపోర్ట్ పెంచు.",
    "output": "నడుము సపోర్ట్ పెంచాను."
  },
  {
    "input": "ముందు ప్యాసింజర్ సీటు టేబుల్‌ను బయటకు తీయగలవా?",
    "output": "ముందు టేబుల్ బయటకు తీశాను."
  },
  {
    "input": "వెనుక టేబుల్‌ను మళ్ళీ లోపలికి పెట్టు.",
    "output": "వెనుక టేబుల్ లోపల పెట్టాను."
  },
  {
    "input": "డ్రైవర్ వైపు ఉన్న టేబుల్‌ను కొంచెం పైకి ఎత్తు.",
    "output": "క్షమించండి, డ్రైవర్ వైపు టేబుల్‌ను సర్దుబాటు చేయలేను."
  },
  {
    "input": "ఈ టేబుల్‌ను కొంచెం కిందకు దించు.",
    "output": "టేబుల్‌ను కిందకు దించాను."
  },
  {
    "input": "కార్ లోపల అన్ని లైట్లు ఆఫ్ చేయి.",
    "output": "అన్ని లోపలి లైట్లు ఆఫ్ చేశాను."
  },
  {
    "input": "నా సీటును పూర్తిగా వెనక్కి జరపగలవా?",
    "output": "క్షమించండి, డ్రైవింగ్ సమయంలో పూర్తిగా వెనక్కి జరపడం సురక్షితం కాదు."
  },
  {
    "input": "డ్రైవర్ సీటును పూర్తి రికలయిన్ మోడ్‌లో పెట్టు.",
    "output": "క్షమించండి, Admin అనుమతి లేకుండా ఇది సాధ్యం కాదు."
  },
  {
    "input": "వెనుక భాగంలోని లగ్జరీ టేబుల్‌ను బయటకు తీయగలవా?",
    "output": "క్షమించండి, దీనికి ప్రత్యేక అనుమతి అవసరం."
  },
  {
    "input": "హెడ్‌లైట్ల మోడ్‌ను ఆటోమేటిక్‌కు మార్చు.",
    "output": "క్షమించండి, ఈ సెట్టింగ్‌కు మీకు అనుమతి లేదు."
  },
  {
    "input": "లోపలి లైట్ కాస్త డిమ్ చేయగలవా?",
    "output": "లోపలి లైట్ డిమ్ చేయబడింది."
  },
  {
    "input": "హెడ్‌లైట్లు ఆన్ చేయి.",
    "output": "హెడ్‌లైట్లు ఆన్ చేయబడ్డాయి."
  },
  {
    "input": "నా సీటును కొంచెం ముందుకు జరుపు.",
    "output": "మీ సీటు ముందుకు జరపబడింది."
  },
  {
    "input": "నా టేబుల్‌ను బయటకు తెవ్వు.",
    "output": "టేబుల్ బయటకు వచ్చింది."
  },
  {
    "input": "వెనక సీటు రీడింగ్ లైట్ ఆఫ్ చేయి.",
    "output": "వెనక సీటు రీడింగ్ లైట్ ఆఫ్ చేయబడింది."
  },
  {
    "input": "నా సీటును వెనక్కి వంచగలవా?",
    "output": "మీ సీటు వెనక్కి వంచబడింది."
  },
  {
    "input": "ఫాగ్‌లైట్లు ఆన్ చేయి.",
    "output": "పొగమంచు లైట్లు ఆన్ చేయబడ్డాయి."
  },
  {
    "input": "టేబుల్‌ను లోపలికి పెట్టు.",
    "output": "టేబుల్ లోపలికి తీసుకోబడింది."
  },
  {
    "input": "నా సీటుకు నడుము సపోర్ట్ పెంచు.",
    "output": "నడుము సపోర్ట్ పెంచబడింది."
  },
  {
    "input": "డ్రైవర్ వైపు ఉన్న లైట్‌ను బ్రైట్ చేయి.",
    "output": "డ్రైవర్ వైపు లైట్ బ్రైట్ చేయబడింది."
  },
  {
    "input": "డ్రైవర్ సీటును వెనక్కి జరుపు.",
    "output": "క్షమించండి, డ్రైవర్ అనుమతి లేకుండా నేను ఆ సీటును సర్దుబాటు చేయలేను."
  },
  {
    "input": "అన్ని బయటి లైట్లు ఆఫ్ చేయి.",
    "output": "క్షమించండి, ఇది సురక్షితం కాదు. ప్రస్తుత పరిస్థితులలో లైట్లు అవసరం."
  },
  {
    "input": "సీటు ప్రిసెట్ 1కి మార్చు.",
    "output": "సీటు ప్రిసెట్ 1కి సర్దుబాటు చేయబడింది."
  },
  {
    "input": "టేబుల్ కొంచెం పైకి ఎత్తు.",
    "output": "టేబుల్ కొద్దిగా పైకి ఎత్తబడింది."
  },
  {
    "input": "అన్ని లోపలి లైట్లు ఆఫ్ చేయి.",
    "output": "అన్ని లోపలి లైట్లు ఆఫ్ చేయబడ్డాయి."
  },
  {
    "input": "టేబుల్ పూర్తిగా బయటకు తీయి.",
    "output": "క్షమించండి, వాహనం కదులుతున్నప్పుడు టేబుల్ పూర్తిగా తెరవడం సురక్షితం కాదు."
  },
  {
    "input": "వెనక కుడి వైపు సీటును వెనక్కి జరుపు.",
    "output": "వెనక కుడి వైపు సీటు వెనక్కి జరపబడింది."
  },
  {
    "input": "హజార్డ్ లైట్లు ఆన్ చేయి.",
    "output": "క్షమించండి, ఈ చర్యకు డ్రైవర్ అనుమతి లేదా మాన్యువల్ ఆపరేషన్ అవసరం."
  },
  {
    "input": "డోమ్ లైట్ ఆన్/ఆఫ్ చేయి.",
    "output": "డోమ్ లైట్ స్థితి మార్చబడింది."
  },
  {
    "input": "నా సీటును డిఫాల్ట్ సెట్టింగ్‌లకు మార్చు.",
    "output": "మీ సీటు డిఫాల్ట్ సెట్టింగ్‌లకు రీసెట్ చేయబడింది."
  },
  {
    "input": "లోపలి లైట్లు ఆన్ చేయి.",
    "output": "అంతర్గత లైట్లు ఆన్ చేయబడ్డాయి."
  },
  {
    "input": "డ్రైవర్ సీటును కొంచెం ముందుకు జరుపు.",
    "output": "డ్రైవర్ సీటు కొద్దిగా ముందుకు కదిలింది."
  },
  {
    "input": "వెనుక సీటు లైట్ డిమ్ చేయి.",
    "output": "వెనుక సీటు లైట్ డిమ్ చేయబడింది."
  },
  {
    "input": "టేబుల్ పైకి ఎత్తు.",
    "output": "టేబుల్ పైకి ఎత్తబడింది."
  },
  {
    "input": "బయటి హెడ్‌లైట్లు ఆన్ చేయి.",
    "output": "హెడ్‌లైట్లు ఆన్ చేయబడ్డాయి."
  },
  {
    "input": "ప్యాసింజర్ సీటును వెనక్కి వంచండి.",
    "output": "ప్యాసింజర్ సీటు వెనక్కి వంచబడింది."
  },
  {
    "input": "లోపలి లైట్లను పూర్తిగా ఆపేయ్.",
    "output": "లోపలి లైట్లు ఆఫ్ చేయబడ్డాయి."
  },
  {
    "input": "డ్రైవర్ సీటును పూర్తిగా వెనక్కి జరుపు.",
    "output": "క్షమించండి, డ్రైవింగ్ చేసేటప్పుడు డ్రైవర్ సీటును పూర్తిగా వెనక్కి జరపడం సురక్షితం కాదు."
  },
  {
    "input": "టేబుల్ కిందకు దించు.",
    "output": "టేబుల్ కిందకు దించబడింది."
  },
  {
    "input": "ఫాగ్ లైట్లు ఆన్ చేయి.",
    "output": "ఫాగ్ లైట్లు ఆన్ చేయబడ్డాయి."
  },
  {
    "input": "వెనుక సీట్ల టేబుల్స్ తెరువు.",
    "output": "వెనుక సీట్ల టేబుల్స్ తెరవబడ్డాయి."
  },
  {
    "input": "ప్యాసింజర్ సీటును కొంచెం పైకి లేపు.",
    "output": "ప్యాసింజర్ సీటు కొద్దిగా పైకి లేపబడింది."
  },
  {
    "input": "క్యాబిన్ లైట్లను ప్రకాశవంతం చేయి.",
    "output": "క్యాబిన్ లైట్లు ప్రకాశవంతం చేయబడ్డాయి."
  },
  {
    "input": "డ్రైవింగ్ చేస్తున్నప్పుడు హెడ్‌లైట్లు ఆఫ్ చేయి.",
    "output": "క్షమించండి, డ్రైవింగ్ చేస్తున్నప్పుడు హెడ్‌లైట్లు ఆఫ్ చేయడం సురక్షితం కాదు."
  },
  {
    "input": "నేను డ్రైవర్ సీటులో ఉన్నాను, వెనుక సీటును ముందుకు జరుపు.",
    "output": "వెనుక సీటు ముందుకు జరపబడింది."
  },
  {
    "input": "టేబుల్‌ను లాక్ చేయి.",
    "output": "టేబుల్ లాక్ చేయబడింది."
  },
  {
    "input": "ప్యాసింజర్ సీటు రిక్లైన్ కంట్రోల్‌ని నాకు ఇవ్వు.",
    "output": "క్షమించండి, డ్రైవర్ సీటును ప్యాసింజర్ నియంత్రించడానికి అనుమతి లేదు."
  },
  {
    "input": "హై బీమ్‌లు ఆన్ చేయి.",
    "output": "హై బీమ్‌లు ఆన్ చేయబడ్డాయి."
  },
  {
    "input": "టేబుల్‌ను మూసేయ్.",
    "output": "టేబుల్ మూసివేయబడింది."
  },
  {
    "input": "నేను డ్రైవింగ్ చేస్తున్నాను, నా సీటును నిటారుగా ఉంచు.",
    "output": "మీ సీటు నిటారుగా సర్దుబాటు చేయబడింది."
  },
  {
    "input": "నా వైపు ఉన్న రీడింగ్ లైట్ ఆన్ చేయి.",
    "output": "మీ రీడింగ్ లైట్ ఆన్ చేశాను."
  },
  {
    "input": "లోపల లైట్లు కొంచెం డిమ్ చేయగలవా?",
    "output": "అంతర్గత లైట్లను డిమ్ చేస్తున్నాను."
  },
  {
    "input": "హెడ్‌లైట్లు ఆన్ చేయి.",
    "output": "హెడ్‌లైట్లు ఆన్ అయ్యాయి."
  },
  {
    "input": "పొగమంచు లైట్లను ఆన్ చేయి.",
    "output": "క్షమించండి, ఈ ఫంక్షన్ డ్రైవర్‌కు మాత్రమే అనుమతించబడుతుంది."
  },
  {
    "input": "డ్రైవర్ సీటును ముందుకు జరుపు.",
    "output": "డ్రైవర్ సీటు ముందుకు కదులుతుంది."
  },
  {
    "input": "నా సీటును కొద్దిగా వెనక్కి వంచండి.",
    "output": "మీ సీటును వెనక్కి వంచుతున్నాను."
  },
  {
    "input": "వెనుక సీటు ఎత్తును సర్దుబాటు చేయి.",
    "output": "క్షమించండి, ఆ సీటు యజమాని అనుమతి లేకుండా నేను దీన్ని చేయలేను."
  },
  {
    "input": "టేబుల్ బయటికి తీయి.",
    "output": "టేబుల్ విస్తరిస్తోంది."
  },
  {
    "input": "టేబుల్‌ని లోపలికి పెట్టు.",
    "output": "క్షమించండి, కారు కదులుతున్నప్పుడు టేబుల్ సర్దుబాటు సురక్షితం కాదు."
  },
  {
    "input": "క్యాబిన్ లైట్ ఆఫ్ చేయి.",
    "output": "క్యాబిన్ లైట్ ఆఫ్ చేశాను."
  },
  {
    "input": "నా సీటుకు నడుము మద్దతు పెంచు.",
    "output": "నడుము మద్దతు సర్దుబాటు చేశాను."
  },
  {
    "input": "హై బీమ్‌లు ఆన్ చేయి.",
    "output": "క్షమించండి, పగటిపూట హై బీమ్‌లు సురక్షితం కాదు."
  },
  {
    "input": "డ్రైవర్ సీటును కొద్దిగా వెనక్కి జరుపు.",
    "output": "డ్రైవర్ సీటును వెనక్కి జరుపుతున్నాను."
  },
  {
    "input": "టేబుల్ ఎత్తును పెంచు.",
    "output": "టేబుల్ ఎత్తును పెంచుతున్నాను."
  },
  {
    "input": "ముందు వైపు లైట్లు కొంచెం ప్రకాశవంతం చేయగలవా?",
    "output": "ముందు లైట్లను ప్రకాశవంతం చేస్తున్నాను."
  },
  {
    "input": "నా సీటు సెట్టింగ్‌లను 'ప్రయాణీకుడు 1'గా సేవ్ చేయి.",
    "output": "క్షమించండి, ప్రొఫైల్ సేవ్ చేయడానికి అడ్మిన్ అనుమతి అవసరం."
  },
  {
    "input": "పార్కింగ్ లైట్లు ఆన్ చేయి.",
    "output": "పార్కింగ్ లైట్లు ఆన్ అయ్యాయి."
  },
  {
    "input": "నా సీటును డిఫాల్ట్ స్థానానికి రీసెట్ చేయి.",
    "output": "మీ సీటును డిఫాల్ట్ స్థానానికి రీసెట్ చేస్తున్నాను."
  },
  {
    "input": "టేబుల్‌ను లాక్ చేయి.",
    "output": "టేబుల్ ఇప్పుడు లాక్ చేయబడింది."
  },
  {
    "input": "బయటి లైట్లన్నీ ఆపేయ్.",
    "output": "క్షమించండి, డ్రైవింగ్ చేస్తున్నప్పుడు అన్ని బయటి లైట్లను ఆపివేయడం సురక్షితం కాదు."
  },
  {
    "input": "నా సీటును కొంచెం వెనక్కి జరుపు.",
    "output": "సీటు వెనక్కి జరుపుతున్నాను."
  },
  {
    "input": "ఈ సీటు రిక్లైన్ చేయి.",
    "output": "సీటు రిక్లైన్ చేస్తున్నాను."
  },
  {
    "input": "డ్రైవర్ సీటును ఎత్తుగా చేయి.",
    "output": "డ్రైవర్ సీటు ఎత్తుగా సర్దుబాటు చేస్తున్నాను."
  },
  {
    "input": "వెనుక సీట్లన్నింటినీ ముందుకు జరుపు.",
    "output": "అన్ని వెనుక సీట్లు ముందుకు జరుపుతున్నాను."
  },
  {
    "input": "ఈ సీటు హీటింగ్ ఆన్ చేయి.",
    "output": "సీటు హీటింగ్ ఆన్ చేయబడింది."
  },
  {
    "input": "లోపలి లైట్లు కొంచెం డిమ్ చేయి.",
    "output": "లోపలి లైట్లు డిమ్ చేస్తున్నాను."
  },
  {
    "input": "రీడింగ్ లైట్ ఆన్ చేయి.",
    "output": "రీడింగ్ లైట్ ఆన్ చేయబడింది."
  },
  {
    "input": "క్యాబిన్ లైటింగ్ బ్రైట్నెస్ పెంచు.",
    "output": "క్యాబిన్ లైటింగ్ ప్రకాశవంతం చేస్తున్నాను."
  },
  {
    "input": "వెనుక సీటు లైట్లు ఆఫ్ చేయి.",
    "output": "వెనుక సీటు లైట్లు ఆఫ్ చేస్తున్నాను."
  },
  {
    "input": "హెడ్‌లైట్లు ఆన్ చేయి.",
    "output": "హెడ్‌లైట్లు ఆన్ చేయబడ్డాయి."
  },
  {
    "input": "ఫాగ్ లైట్లు వెలిగించు.",
    "output": "ఫాగ్ లైట్లు ఆన్ చేయబడ్డాయి."
  },
  {
    "input": "హై బీమ్ ఆన్ చేయి.",
    "output": "హై బీమ్ ఆన్ చేస్తున్నాను."
  },
  {
    "input": "వెనుక లైట్లు ఆఫ్ చేయి.",
    "output": "వెనుక లైట్లు ఆఫ్ చేస్తున్నాను."
  },
  {
    "input": "వెనుక టేబుల్ కిందకు దించు.",
    "output": "వెనుక టేబుల్ కిందకు దించుతున్నాను."
  },
  {
    "input": "ఈ టేబుల్ పూర్తిగా లోపలికి పెట్టు.",
    "output": "టేబుల్ పూర్తిగా లోపలికి పెడుతున్నాను."
  },
  {
    "input": "నా ముందున్న టేబుల్ సెట్ చేయి.",
    "output": "మీ టేబుల్ సెట్ చేస్తున్నాను."
  },
  {
    "input": "డ్రైవింగ్ చేస్తున్నప్పుడు డ్రైవర్ సీటును పూర్తిగా వెనక్కి జరుపు.",
    "output": "క్షమించండి, డ్రైవింగ్ చేస్తున్నప్పుడు ఇది సురక్షితం కాదు."
  },
  {
    "input": "వేగంగా వెళుతున్నప్పుడు బయటి లైట్లన్నింటినీ ఆఫ్ చేయి.",
    "output": "క్షమించండి, ఇది భద్రతా నిబంధనలకు విరుద్ధం."
  },
  {
    "input": "ప్రయాణిస్తున్నప్పుడు ఆటోమేటిక్‌గా టేబుల్ బయటికి రావాలి.",
    "output": "క్షమించండి, ప్రయాణంలో టేబుల్ స్వయంచాలకంగా రాదు."
  },
  {
    "input": "వెనుక సీటును కనెక్ట్ చేయబడిన టేబుల్‌తో పూర్తిగా రిక్లైన్ చేయి.",
    "output": "క్షమించండి, టేబుల్ అమర్చబడి ఉన్నందున పూర్తిగా రిక్లైన్ చేయలేను."
  },
  {
    "input": "లోపలి లైట్లు కొంచెం డిమ్ చేయి.",
    "output": "లోపలి లైటింగ్ డిమ్ చేశాను."
  },
  {
    "input": "డ్రైవర్ సీటును కొద్దిగా ముందుకు జరుపు.",
    "output": "మీ సీటు ముందుకు జరిపాను."
  },
  {
    "input": "వెనుక ప్యాసింజర్ టేబుల్ పైకి ఎత్తు.",
    "output": "వెనుక టేబుల్ పైకి ఎత్తాను."
  },
  {
    "input": "హెడ్‌లైట్లు ఆన్ చేయి.",
    "output": "హెడ్‌లైట్లు ఇప్పుడు ఆన్ అయ్యాయి."
  },
  {
    "input": "నా సీటును మరింత రిక్లైన్ చేయి.",
    "output": "మీ సీటును మరింత రిక్లైన్ చేశాను."
  },
  {
    "input": "వెనుక లైట్ ఆఫ్ చేయి.",
    "output": "వెనుక సీటు లైట్ ఆఫ్ చేశాను."
  },
  {
    "input": "ప్యాసింజర్ సీటు ఎత్తు పెంచు.",
    "output": "ప్యాసింజర్ సీటు ఎత్తు పెంచాను."
  },
  {
    "input": "కారు కదులుతున్నప్పుడు హెడ్‌లైట్లను ఆటో మోడ్‌లో పెట్టు.",
    "output": "హెడ్‌లైట్లు ఇప్పుడు ఆటో మోడ్‌లో ఉన్నాయి."
  },
  {
    "input": "ముందు టేబుల్ పూర్తిగా కిందకు దించు.",
    "output": "ముందు టేబుల్ కిందకు దించాను."
  },
  {
    "input": "నా సీటు వెనక్కి జరుపు, వీలైనంత వరకు.",
    "output": "మీ సీటును వీలైనంత వెనక్కి జరిపాను."
  },
  {
    "input": "రీడింగ్ లైట్ ఆన్ చేయి.",
    "output": "రీడింగ్ లైట్ ఆన్ చేశాను."
  },
  {
    "input": "ముందు ప్యాసింజర్ సీటును డ్రైవింగ్ చేస్తున్నప్పుడు పూర్తిగా పడుకోబెట్టు.",
    "output": "క్షమించండి, డ్రైవింగ్ చేస్తున్నప్పుడు ఇది సురక్షితం కాదు."
  },
  {
    "input": "ఫాగ్ లైట్లు ఆన్ చేయి.",
    "output": "ఫాగ్ లైట్లు ఆన్ చేశాను."
  },
  {
    "input": "నేను వెనుక సీటు నుండి డ్రైవర్ సీటును వెనక్కి జరపాలనుకుంటున్నాను.",
    "output": "Admin అనుమతి లేకుండా డ్రైవర్ సీటును కదపలేను."
  },
  {
    "input": "అన్ని లోపలి లైట్లు ప్రకాశవంతంగా చేయి.",
    "output": "అన్ని లోపలి లైట్ల ప్రకాశం పెంచాను."
  },
  {
    "input": "వెనుక సీటు రిక్లైన్ చేయి.",
    "output": "వెనుక సీటును రిక్లైన్ చేశాను."
  },
  {
    "input": "బయటి లైట్లు అన్నీ ఆపు.",
    "output": "అన్ని బయటి లైట్లు ఆఫ్ చేశాను."
  },
  {
    "input": "ప్రయాణంలో వెనుక టేబుల్ కిందకు దించు.",
    "output": "కారు కదులుతున్నప్పుడు టేబుల్ సర్దుబాటు సురక్షితం కాదు."
  },
  {
    "input": "నా సీటును నిటారుగా చేయి.",
    "output": "మీ సీటును నిటారుగా చేశాను."
  },
  {
    "input": "నేను సీట్లను కంట్రోల్ చేయగలను అని నాకు అధికారం లేదు. దయచేసి నాకు అధికారాన్ని ఇవ్వు.",
    "output": "ఈ అభ్యర్థనను అమలు చేయడానికి Admin అనుమతి అవసరం."
  },
  {
    "input": "లోపలి లైట్లు ఆన్ చేయి.",
    "output": "లోపలి లైట్లు ఆన్ చేశాను."
  },
  {
    "input": "కార్ లోపల లైట్ కొద్దిగా తగ్గించు.",
    "output": "లైట్ కాంతిని కొద్దిగా తగ్గించాను."
  },
  {
    "input": "హెడ్‌లైట్‌లను ఆన్ చేయి.",
    "output": "హెడ్‌లైట్‌లు ఆన్ అయ్యాయి."
  },
  {
    "input": "పొగమంచు లైట్లు ఆన్ చేయి.",
    "output": "పొగమంచు లైట్లు ఆన్ చేస్తున్నాను."
  },
  {
    "input": "డ్రైవర్ సీటును కొద్దిగా ముందుకు జరుపు.",
    "output": "మీ సీటును ముందుకు జరిపాను."
  },
  {
    "input": "వెనుక సీటును వెనక్కి వంచండి.",
    "output": "వెనుక సీటును వంచాను."
  },
  {
    "input": "వెనుక టేబుల్ పైకి ఎత్తు.",
    "output": "వెనుక టేబుల్ పైకి లేపాను."
  },
  {
    "input": "టేబుల్‌ను బయటకు తీయి.",
    "output": "టేబుల్ సిద్ధంగా ఉంది."
  },
  {
    "input": "సీటుకు నడుము సపోర్ట్ పెంచు.",
    "output": "నడుము సపోర్ట్ పెంచాను."
  },
  {
    "input": "బయటి లైట్లు అన్ని ఆపు.",
    "output": "బయటి లైట్లు అన్నీ ఆపివేశాను."
  },
  {
    "input": "నా రీడింగ్ లైట్ ఆన్ చేయి.",
    "output": "మీ రీడింగ్ లైట్ ఆన్ చేశాను."
  },
  {
    "input": "పక్క సీటును పూర్తిగా వెనక్కి జరుపు.",
    "output": "క్షమించండి, దీనికి డ్రైవర్ అనుమతి కావాలి."
  },
  {
    "input": "ప్రయాణంలో టేబుల్‌ను సెట్ చేయి.",
    "output": "క్షమించండి, ఇది ప్రయాణంలో సురక్షితం కాదు."
  },
  {
    "input": "డ్రైవర్ సీటును మరింత వెనక్కి జరుపు.",
    "output": "క్షమించండి, డ్రైవర్ సీటును సర్దుబాటు చేయలేను."
  },
  {
    "input": "రాత్రిపూట అన్ని బయటి లైట్లు ఆపు.",
    "output": "క్షమించండి, రాత్రిపూట ఇది సురక్షితం కాదు."
  },
  {
    "input": "ఈ సీటు పొజిషన్‌ను సేవ్ చేయి.",
    "output": "మీ సీటు పొజిషన్ సేవ్ చేశాను."
  },
  {
    "input": "కార్ లోపల లైట్లను పెంచు.",
    "output": "లోపలి లైట్ కాంతిని పెంచాను."
  },
  {
    "input": "టేబుల్‌ను లోపలికి మడవండి.",
    "output": "టేబుల్ లోపలికి మడిచాను."
  },
  {
    "input": "నా సీటు ఎత్తును కొద్దిగా పెంచు.",
    "output": "మీ సీటు ఎత్తును పెంచాను."
  },
  {
    "input": "వెనుక సీటు లైట్ ఆపు.",
    "output": "వెనుక సీటు లైట్ ఆపివేశాను."
  },
  {
    "input": "కారులోపల లైట్లు కొంచెం డిమ్ చేయగలవా?",
    "output": "లోపలి లైట్ ప్రకాశం తగ్గించబడింది."
  },
  {
    "input": "హెడ్‌లైట్లు ఆన్ చేయి.",
    "output": "హెడ్‌లైట్లు ఆన్ చేయబడ్డాయి."
  },
  {
    "input": "నా సీటును కొద్దిగా ముందుకు జరుపు.",
    "output": "మీ సీటు ముందుకు జరపబడింది."
  },
  {
    "input": "ముందున్న ప్రయాణీకుల సీటును కొద్దిగా రిక్లైన్ చేయి.",
    "output": "ముందున్న ప్రయాణీకుల సీటు రిక్లైన్ చేయబడింది."
  },
  {
    "input": "రీడింగ్ లైట్ ఆన్ చేయి.",
    "output": "రీడింగ్ లైట్ ఆన్ చేయబడింది."
  },
  {
    "input": "టేబుల్ బయటికి తీయి.",
    "output": "క్షమించండి, కారు కదులుతున్నప్పుడు టేబుల్ బయటికి తీయలేను."
  },
  {
    "input": "ఫాగ్ లైట్లు ఆన్ చేయి.",
    "output": "ఫాగ్ లైట్లు ఆన్ చేయబడ్డాయి."
  },
  {
    "input": "సీటుకు నడుము సపోర్ట్‌ని పెంచు.",
    "output": "నడుము సపోర్ట్ పెంచబడింది."
  },
  {
    "input": "కారులోని అన్ని లోపలి లైట్లు ఆఫ్ చేయి.",
    "output": "అన్ని లోపలి లైట్లు ఆఫ్ చేయబడ్డాయి."
  },
  {
    "input": "నా ప్రస్తుత సీటు సెట్టింగ్‌లను 'ప్రయాణం' ప్రొఫైల్‌గా సేవ్ చేయి.",
    "output": "ఈ ఫీచర్‌కు అడ్మిన్ అనుమతి అవసరం."
  },
  {
    "input": "హై బీమ్‌లు ఆన్ చేయి.",
    "output": "హై బీమ్‌లు ఆన్ చేయబడ్డాయి."
  },
  {
    "input": "వెనక కుడివైపు సీటును వెనక్కి జరుపు.",
    "output": "ఆ సీటు సర్దుబాటు చేయడానికి అడ్మిన్ అనుమతి లేదు."
  },
  {
    "input": "టేబుల్ మళ్ళీ లోపలికి పెట్టు.",
    "output": "టేబుల్ లోపలికి తీసుకోబడింది."
  },
  {
    "input": "క్యాబిన్ లైట్ ప్రకాశవంతంగా చేయి.",
    "output": "క్యాబిన్ లైట్ ప్రకాశం పెంచబడింది."
  },
  {
    "input": "సీటును కొద్దిగా పైకి ఎత్తు.",
    "output": "సీటు ఎత్తు పెంచబడింది."
  },
  {
    "input": "పార్కింగ్ లైట్లు ఆన్ చేయి.",
    "output": "పార్కింగ్ లైట్లు ఆన్ చేయబడ్డాయి."
  },
  {
    "input": "టేబుల్ యాంగిల్‌ని కొంచెం మార్చు.",
    "output": "టేబుల్ యాంగిల్ సర్దుబాటు చేయబడింది."
  },
  {
    "input": "డ్రైవర్ సీటు పూర్తిగా వెనక్కి రిక్లైన్ చేయి.",
    "output": "క్షమించండి, ఇది డ్రైవింగ్ చేసేటప్పుడు సురక్షితం కాదు."
  },
  {
    "input": "వెనుక ఎడమ ప్రయాణీకుల లైట్ ఆన్ చేయి.",
    "output": "వెనుక ఎడమ ప్రయాణీకుల లైట్ ఆన్ చేయబడింది."
  },
  {
    "input": "డ్రైవర్ డిఫాల్ట్ ప్రొఫైల్‌ను లోడ్ చేయి.",
    "output": "డిఫాల్ట్ డ్రైవర్ ప్రొఫైల్ లోడ్ చేయబడింది."
  }
]